odoo/addons/l10n_ro_stock_report/README.rst
odoo/addons/l10n_ro_stock_report/__init__.py
odoo/addons/l10n_ro_stock_report/__manifest__.py
odoo/addons/l10n_ro_stock_report/i18n/l10n_ro_stock_report.pot
odoo/addons/l10n_ro_stock_report/i18n/ro.po
odoo/addons/l10n_ro_stock_report/readme/CONTRIBUTORS.md
odoo/addons/l10n_ro_stock_report/readme/DESCRIPTION.md
odoo/addons/l10n_ro_stock_report/readme/INSTALL.md
odoo/addons/l10n_ro_stock_report/report/__init__.py
odoo/addons/l10n_ro_stock_report/report/stock_report.py
odoo/addons/l10n_ro_stock_report/report/stock_report_template.xml
odoo/addons/l10n_ro_stock_report/report/stock_report_view.xml
odoo/addons/l10n_ro_stock_report/security/ir.model.access.csv
odoo/addons/l10n_ro_stock_report/static/description/icon.png
odoo/addons/l10n_ro_stock_report/static/description/index.html
odoo/addons/l10n_ro_stock_report/static/src/css/report.css
odoo/addons/l10n_ro_stock_report/tests/__init__.py
odoo/addons/l10n_ro_stock_report/tests/test_report_stock.py
odoo_addon_l10n_ro_stock_report-18.0.1.6.0.dist-info/METADATA
odoo_addon_l10n_ro_stock_report-18.0.1.6.0.dist-info/WHEEL
odoo_addon_l10n_ro_stock_report-18.0.1.6.0.dist-info/top_level.txt
odoo_addon_l10n_ro_stock_report-18.0.1.6.0.dist-info/RECORD
