Metadata-Version: 2.1
Name: odoo-addon-l10n_ro_stock_report
Version: 18.0.1.6.0
Requires-Python: >=3.10
Requires-Dist: odoo-addon-l10n_ro_stock_account==18.0.*
Requires-Dist: odoo==18.0.*
Summary: =?utf-8?q?Romania_-_Stock_Report_=28Fi=C8=99=C4=83_Magazie=29?=
Home-page: https://github.com/OCA/l10n-romania
License: AGPL-3
Author: Terrabit,NextERP Romania,Odoo Community Association (OCA)
Author-email: support@odoo-community.org
Classifier: Programming Language :: Python
Classifier: Framework :: Odoo
Classifier: Framework :: Odoo :: 18.0
Classifier: License :: OSI Approved :: GNU Affero General Public License v3
Classifier: Development Status :: 6 - Mature
